TPDNE_utils/__init__.py
TPDNE_utils/nginx.conf.tmpl
TPDNE_utils/tpdne.py
TPDNE_utils/tpdne.service.tmpl
TPDNE_utils-0.0.11.dist-info/LICENSE
TPDNE_utils-0.0.11.dist-info/METADATA
TPDNE_utils-0.0.11.dist-info/WHEEL
TPDNE_utils-0.0.11.dist-info/top_level.txt
TPDNE_utils-0.0.11.dist-info/RECORD
