Metadata-Version: 2.1
Name: TPDNE-utils
Version: 0.0.11
Summary: TPDNE
Home-page: https://github.com/lucidrains/TPDNE
Author: Phil Wang
Author-email: lucidrains@gmail.com
License: MIT
Keywords: thispersondoesnotexist
Classifier: Development Status :: 4 - Beta
Classifier: Intended Audience :: Developers
Classifier: Topic :: Scientific/Engineering :: Artificial Intelligence
Classifier: License :: OSI Approved :: MIT License
Classifier: Programming Language :: Python :: 3.6
License-File: LICENSE
Requires-Dist: beartype
Requires-Dist: einops >=0.6
Requires-Dist: jinja2
Requires-Dist: numpy
Requires-Dist: pillow
